<annotation>
	<folder></folder>
	<filename>frame159_jpg.rf.c9c10748ee6016b037837b72a51b4bbe.jpg</filename>
	<path>frame159_jpg.rf.c9c10748ee6016b037837b72a51b4bbe.jpg</path>
	<source>
		<database>roboflow.ai</database>
	</source>
	<size>
		<width>416</width>
		<height>416</height>
		<depth>3</depth>
	</size>
	<segmented>0</segmented>
	<object>
		<name>mature</name>
		<pose>Unspecified</pose>
		<truncated>0</truncated>
		<difficult>0</difficult>
		<occluded>0</occluded>
		<bndbox>
			<xmin>168</xmin>
			<xmax>197</xmax>
			<ymin>126</ymin>
			<ymax>179</ymax>
		</bndbox>
	</object>
	<object>
		<name>mature</name>
		<pose>Unspecified</pose>
		<truncated>0</truncated>
		<difficult>0</difficult>
		<occluded>0</occluded>
		<bndbox>
			<xmin>124</xmin>
			<xmax>153</xmax>
			<ymin>182</ymin>
			<ymax>226</ymax>
		</bndbox>
	</object>
	<object>
		<name>mature</name>
		<pose>Unspecified</pose>
		<truncated>0</truncated>
		<difficult>0</difficult>
		<occluded>0</occluded>
		<bndbox>
			<xmin>127</xmin>
			<xmax>163</xmax>
			<ymin>207</ymin>
			<ymax>254</ymax>
		</bndbox>
	</object>
	<object>
		<name>mature</name>
		<pose>Unspecified</pose>
		<truncated>0</truncated>
		<difficult>0</difficult>
		<occluded>0</occluded>
		<bndbox>
			<xmin>157</xmin>
			<xmax>193</xmax>
			<ymin>204</ymin>
			<ymax>253</ymax>
		</bndbox>
	</object>
	<object>
		<name>mature</name>
		<pose>Unspecified</pose>
		<truncated>0</truncated>
		<difficult>0</difficult>
		<occluded>0</occluded>
		<bndbox>
			<xmin>145</xmin>
			<xmax>182</xmax>
			<ymin>149</ymin>
			<ymax>206</ymax>
		</bndbox>
	</object>
	<object>
		<name>young</name>
		<pose>Unspecified</pose>
		<truncated>0</truncated>
		<difficult>0</difficult>
		<occluded>0</occluded>
		<bndbox>
			<xmin>142</xmin>
			<xmax>164</xmax>
			<ymin>137</ymin>
			<ymax>166</ymax>
		</bndbox>
	</object>
	<object>
		<name>intermediate</name>
		<pose>Unspecified</pose>
		<truncated>0</truncated>
		<difficult>0</difficult>
		<occluded>0</occluded>
		<bndbox>
			<xmin>86</xmin>
			<xmax>106</xmax>
			<ymin>156</ymin>
			<ymax>187</ymax>
		</bndbox>
	</object>
	<object>
		<name>mature</name>
		<pose>Unspecified</pose>
		<truncated>0</truncated>
		<difficult>0</difficult>
		<occluded>0</occluded>
		<bndbox>
			<xmin>68</xmin>
			<xmax>91</xmax>
			<ymin>177</ymin>
			<ymax>215</ymax>
		</bndbox>
	</object>
	<object>
		<name>intermediate</name>
		<pose>Unspecified</pose>
		<truncated>0</truncated>
		<difficult>0</difficult>
		<occluded>0</occluded>
		<bndbox>
			<xmin>53</xmin>
			<xmax>71</xmax>
			<ymin>182</ymin>
			<ymax>218</ymax>
		</bndbox>
	</object>
	<object>
		<name>mature</name>
		<pose>Unspecified</pose>
		<truncated>0</truncated>
		<difficult>0</difficult>
		<occluded>0</occluded>
		<bndbox>
			<xmin>60</xmin>
			<xmax>84</xmax>
			<ymin>225</ymin>
			<ymax>265</ymax>
		</bndbox>
	</object>
	<object>
		<name>intermediate</name>
		<pose>Unspecified</pose>
		<truncated>0</truncated>
		<difficult>0</difficult>
		<occluded>0</occluded>
		<bndbox>
			<xmin>46</xmin>
			<xmax>62</xmax>
			<ymin>230</ymin>
			<ymax>257</ymax>
		</bndbox>
	</object>
	<object>
		<name>young</name>
		<pose>Unspecified</pose>
		<truncated>0</truncated>
		<difficult>0</difficult>
		<occluded>0</occluded>
		<bndbox>
			<xmin>4</xmin>
			<xmax>9</xmax>
			<ymin>145</ymin>
			<ymax>168</ymax>
		</bndbox>
	</object>
	<object>
		<name>young</name>
		<pose>Unspecified</pose>
		<truncated>0</truncated>
		<difficult>0</difficult>
		<occluded>0</occluded>
		<bndbox>
			<xmin>220</xmin>
			<xmax>241</xmax>
			<ymin>334</ymin>
			<ymax>352</ymax>
		</bndbox>
	</object>
	<object>
		<name>young</name>
		<pose>Unspecified</pose>
		<truncated>0</truncated>
		<difficult>0</difficult>
		<occluded>0</occluded>
		<bndbox>
			<xmin>256</xmin>
			<xmax>267</xmax>
			<ymin>233</ymin>
			<ymax>249</ymax>
		</bndbox>
	</object>
	<object>
		<name>young</name>
		<pose>Unspecified</pose>
		<truncated>0</truncated>
		<difficult>0</difficult>
		<occluded>0</occluded>
		<bndbox>
			<xmin>250</xmin>
			<xmax>262</xmax>
			<ymin>148</ymin>
			<ymax>168</ymax>
		</bndbox>
	</object>
	<object>
		<name>young</name>
		<pose>Unspecified</pose>
		<truncated>0</truncated>
		<difficult>0</difficult>
		<occluded>0</occluded>
		<bndbox>
			<xmin>238</xmin>
			<xmax>247</xmax>
			<ymin>165</ymin>
			<ymax>182</ymax>
		</bndbox>
	</object>
	<object>
		<name>intermediate</name>
		<pose>Unspecified</pose>
		<truncated>0</truncated>
		<difficult>0</difficult>
		<occluded>0</occluded>
		<bndbox>
			<xmin>245</xmin>
			<xmax>256</xmax>
			<ymin>96</ymin>
			<ymax>111</ymax>
		</bndbox>
	</object>
	<object>
		<name>young</name>
		<pose>Unspecified</pose>
		<truncated>0</truncated>
		<difficult>0</difficult>
		<occluded>0</occluded>
		<bndbox>
			<xmin>202</xmin>
			<xmax>213</xmax>
			<ymin>57</ymin>
			<ymax>73</ymax>
		</bndbox>
	</object>
</annotation>
