<annotation>
	<folder></folder>
	<filename>frame167_jpg.rf.8f74d505f6459759a8b08eba297efc18.jpg</filename>
	<path>frame167_jpg.rf.8f74d505f6459759a8b08eba297efc18.jpg</path>
	<source>
		<database>roboflow.ai</database>
	</source>
	<size>
		<width>416</width>
		<height>416</height>
		<depth>3</depth>
	</size>
	<segmented>0</segmented>
	<object>
		<name>mature</name>
		<pose>Unspecified</pose>
		<truncated>0</truncated>
		<difficult>0</difficult>
		<occluded>0</occluded>
		<bndbox>
			<xmin>7</xmin>
			<xmax>23</xmax>
			<ymin>106</ymin>
			<ymax>135</ymax>
		</bndbox>
	</object>
	<object>
		<name>intermediate</name>
		<pose>Unspecified</pose>
		<truncated>0</truncated>
		<difficult>0</difficult>
		<occluded>0</occluded>
		<bndbox>
			<xmin>21</xmin>
			<xmax>35</xmax>
			<ymin>103</ymin>
			<ymax>142</ymax>
		</bndbox>
	</object>
	<object>
		<name>young</name>
		<pose>Unspecified</pose>
		<truncated>0</truncated>
		<difficult>0</difficult>
		<occluded>0</occluded>
		<bndbox>
			<xmin>143</xmin>
			<xmax>163</xmax>
			<ymin>151</ymin>
			<ymax>174</ymax>
		</bndbox>
	</object>
	<object>
		<name>mature</name>
		<pose>Unspecified</pose>
		<truncated>0</truncated>
		<difficult>0</difficult>
		<occluded>0</occluded>
		<bndbox>
			<xmin>208</xmin>
			<xmax>225</xmax>
			<ymin>271</ymin>
			<ymax>294</ymax>
		</bndbox>
	</object>
	<object>
		<name>mature</name>
		<pose>Unspecified</pose>
		<truncated>0</truncated>
		<difficult>0</difficult>
		<occluded>0</occluded>
		<bndbox>
			<xmin>224</xmin>
			<xmax>241</xmax>
			<ymin>246</ymin>
			<ymax>273</ymax>
		</bndbox>
	</object>
	<object>
		<name>intermediate</name>
		<pose>Unspecified</pose>
		<truncated>0</truncated>
		<difficult>0</difficult>
		<occluded>0</occluded>
		<bndbox>
			<xmin>237</xmin>
			<xmax>250</xmax>
			<ymin>244</ymin>
			<ymax>269</ymax>
		</bndbox>
	</object>
	<object>
		<name>young</name>
		<pose>Unspecified</pose>
		<truncated>0</truncated>
		<difficult>0</difficult>
		<occluded>0</occluded>
		<bndbox>
			<xmin>72</xmin>
			<xmax>82</xmax>
			<ymin>325</ymin>
			<ymax>342</ymax>
		</bndbox>
	</object>
</annotation>
